doc_relax-0.0.2a6.dist-info/licenses/LICENSE
relax/__init__.py
relax/__version__.py
relax/relax.py
relax/RelaxCore/RelaxCore.py
relax/RelaxCore/__init__.py
doc_relax-0.0.2a6.dist-info/METADATA
doc_relax-0.0.2a6.dist-info/WHEEL
doc_relax-0.0.2a6.dist-info/entry_points.txt
doc_relax-0.0.2a6.dist-info/top_level.txt
doc_relax-0.0.2a6.dist-info/RECORD
