Metadata-Version: 2.4
Name: doc-relax
Version: 0.0.2a6
Summary: ReLaX (Rendering Environment for LaTeX) is a rendering framework designed to automate the creation of documents using LaTeX-based templates.
Home-page: https://github.com/AgustinDoCanto/ReLaX
Author: Agustin Do Canto
Author-email: docantocontacto@gmail.com
Project-URL: Bug Tracker, https://github.com/AgustinDoCanto/ReLaX/issues
Project-URL: Documentation, https://github.com/AgustinDoCanto/ReLaX#readme
Project-URL: Source Code, https://github.com/AgustinDoCanto/ReLaX
Classifier: Programming Language :: Python :: 3
Classifier: License :: OSI Approved :: GNU General Public License v3 (GPLv3)
Classifier: Operating System :: OS Independent
Requires-Python: >=3.9
License-File: LICENSE
Requires-Dist: click
Requires-Dist: jinja2
Dynamic: author
Dynamic: author-email
Dynamic: classifier
Dynamic: description
Dynamic: description-content-type
Dynamic: home-page
Dynamic: license-file
Dynamic: project-url
Dynamic: requires-dist
Dynamic: requires-python
Dynamic: summary
